{
  "original_count": 192,
  "vif_analysis_count": 122,
  "removed_by_vif": 70,
  "features": [
    "oil_close",
    "returns_5d_lag_2",
    "returns_5d_lag_1",
    "returns_21d_rolling_10_std",
    "returns_5d_rolling_252_mean",
    "returns_1d_rolling_63_max",
    "returns_252d_rolling_21_std",
    "volume_rolling_63_mean",
    "returns_5d_rolling_10_max",
    "returns_21d_lag_21",
    "volume_ratio",
    "returns_5d_lag_5",
    "returns_1d_rolling_21_max",
    "returns_1d_rolling_10_max",
    "volume_rolling_5_min",
    "returns_5d_rolling_10_std",
    "returns_5d_lag_3",
    "volatility_21d_lag_63",
    "returns_63d_rolling_21_std",
    "volume_rolling_10_max",
    "volatility_5d_lag_5",
    "returns_21d_rolling_21_std",
    "volume_rolling_10_min",
    "returns_252d_rolling_10_std",
    "returns_5d_rolling_5_std",
    "etf_flow_21d_sum",
    "volume_rolling_21_max",
    "returns_63d_rolling_10_std",
    "returns_21d_rolling_5_std",
    "volatility_5d_lag_10",
    "volume_lag_3",
    "returns_63d_rolling_5_std",
    "volatility_5d_lag_21",
    "returns_252d_rolling_5_std",
    "returns_5d_lag_21",
    "returns_5d_lag_10",
    "etf_flow_5d_sum",
    "oil_corr",
    "volume_lag_2",
    "volume_lag_1",
    "volatility_5d_lag_63",
    "copper_corr",
    "high_low_ratio",
    "high_low_ratio_lag_1",
    "sp500_corr",
    "high_low_ratio_lag_2",
    "high_low_ratio_lag_3",
    "etf_daily_flow_usd",
    "high_low_ratio_lag_5",
    "log_returns_1d",
    "returns_5d_lag_63",
    "gold_silver_corr",
    "high_low_ratio_lag_10",
    "gold_silver_ratio_change",
    "volume_lag_5",
    "close_open_ratio",
    "high_low_ratio_lag_21",
    "log_returns_1d_lag_3",
    "log_returns_1d_lag_1",
    "log_returns_1d_lag_5",
    "etf_flow_signal",
    "high_low_ratio_lag_63",
    "log_returns_1d_lag_21",
    "log_returns_1d_lag_2",
    "log_returns_1d_lag_10",
    "log_returns_1d_lag_63",
    "volume_lag_63",
    "volume_lag_10",
    "volume_lag_21",
    "close_open_ratio_lag_5",
    "close_open_ratio_lag_1",
    "close_open_ratio_lag_21",
    "close_open_ratio_lag_10",
    "obv_ma_ratio",
    "close_open_ratio_lag_3",
    "close_open_ratio_lag_63",
    "death_cross",
    "golden_cross",
    "close_open_ratio_lag_2",
    "returns_1d_rolling_252_min",
    "copper_close",
    "returns_5d_rolling_252_max",
    "returns_21d_rolling_252_max",
    "obv",
    "returns_21d_rolling_63_std",
    "returns_21d_rolling_252_min",
    "returns_21d_rolling_21_min",
    "returns_1d_rolling_5_min",
    "returns_21d_rolling_21_max",
    "returns_5d_rolling_5_min",
    "returns_21d_rolling_63_max",
    "rsi_14",
    "volatility_5d_lag_1",
    "returns_5d_rolling_63_max",
    "returns_5d_rolling_252_min",
    "returns_5d_rolling_10_min",
    "volume",
    "returns_5d_rolling_5_max",
    "returns_21d_rolling_63_min",
    "volatility_5d_lag_2",
    "volume_rolling_63_max",
    "bb_position",
    "returns_63d_rolling_252_min",
    "returns_1d_rolling_63_min",
    "returns_1d_rolling_10_min",
    "returns_5d_rolling_21_min",
    "returns_63d_lag_63",
    "open_rolling_10_std",
    "returns_21d_lag_63",
    "volatility_5d",
    "returns_5d_rolling_21_std",
    "returns_5d",
    "returns_21d_lag_10",
    "volatility_21d_lag_21",
    "returns_1d_rolling_252_max",
    "returns_5d_rolling_63_min",
    "returns_1d_rolling_252_mean",
    "returns_1d_rolling_5_max",
    "returns_1d_rolling_21_min",
    "volatility_5d_lag_3",
    "returns_5d_rolling_21_max",
    "close_sma_5_ratio"
  ],
  "vif_summary": {
    "mean_vif": 16.118268644459878,
    "max_vif": 426.85651931297184,
    "min_vif": 1.0007215064650907
  }
}